cursor_dungeon_master-0.4.1.dist-info/licenses/LICENSE
dungeon_master/__init__.py
dungeon_master/cli.py
dungeon_master/commands/__init__.py
dungeon_master/commands/create_lore.py
dungeon_master/commands/init.py
dungeon_master/commands/map.py
dungeon_master/commands/review.py
dungeon_master/commands/validate.py
dungeon_master/core/__init__.py
dungeon_master/core/decorator_parser.py
dungeon_master/core/git_utils.py
dungeon_master/core/template.py
dungeon_master/core/validation.py
dungeon_master/hooks/__init__.py
dungeon_master/hooks/pre_commit.py
dungeon_master/templates/gitignore.template
dungeon_master/templates/cursor_rules/dungeon_master_commands.mdc
dungeon_master/templates/cursor_rules/dungeon_master_enforcement.mdc
dungeon_master/templates/cursor_rules/dungeon_master_template.mdc
dungeon_master/templates/cursor_rules/dungeon_master_workflow.mdc
dungeon_master/utils/__init__.py
dungeon_master/utils/config.py
dungeon_master/utils/cursor_setup.py
dungeon_master/utils/file_utils.py
cursor_dungeon_master-0.4.1.dist-info/METADATA
cursor_dungeon_master-0.4.1.dist-info/WHEEL
cursor_dungeon_master-0.4.1.dist-info/entry_points.txt
cursor_dungeon_master-0.4.1.dist-info/top_level.txt
cursor_dungeon_master-0.4.1.dist-info/RECORD
